bobleesj/__init__.py
bobleesj/utils/__init__.py
bobleesj/utils/app.py
bobleesj/utils/numbers.py
bobleesj/utils/version.py
bobleesj/utils/cli/api.py
bobleesj/utils/cli/auth.py
bobleesj/utils/cli/shell.py
bobleesj/utils/cli/test.py
bobleesj/utils/cli/create/gif.py
bobleesj/utils/cli/create/issues.py
bobleesj/utils/cli/delete/branch.py
bobleesj/utils/data/element.py
bobleesj/utils/data/db/oliynyk-elemental-property-list.xlsx
bobleesj/utils/io/config.py
bobleesj/utils/io/folder.py
bobleesj/utils/parsers/__init__.py
bobleesj/utils/parsers/formula.py
bobleesj/utils/sorters/element_sorter.py
bobleesj/utils/sources/__init__.py
bobleesj/utils/sources/mendeleev.py
bobleesj/utils/sources/oliynyk.py
bobleesj/utils/sources/ptable.py
bobleesj/utils/sources/radius.py
bobleesj_utils-0.0.5.dist-info/licenses/AUTHORS.rst
bobleesj_utils-0.0.5.dist-info/licenses/LICENSE.rst
bobleesj_utils-0.0.5.dist-info/METADATA
bobleesj_utils-0.0.5.dist-info/WHEEL
bobleesj_utils-0.0.5.dist-info/entry_points.txt
bobleesj_utils-0.0.5.dist-info/top_level.txt
bobleesj_utils-0.0.5.dist-info/RECORD
