Metadata-Version: 2.4
Name: bobleesj.utils
Version: 0.0.5
Summary: Python package for sharing utility functions and classes in materials informatics.
Author-email: Sangjoon Lee <bobleesj@gmail.com>
Maintainer-email: Sangjoon Lee <bobleesj@gmail.com>
Project-URL: Homepage, https://bobleesj.github.io/bobleesj.utils/
Project-URL: Issues, https://github.com/bobleesj/bobleesj.utils/issues/
Keywords: science,utility,chemistry
Classifier: Development Status :: 5 - Production/Stable
Classifier: Environment :: Console
Classifier: Intended Audience :: Developers
Classifier: Intended Audience :: Science/Research
Classifier: License :: OSI Approved :: BSD License
Classifier: Operating System :: MacOS :: MacOS X
Classifier: Operating System :: Microsoft :: Windows
Classifier: Operating System :: POSIX
Classifier: Operating System :: Unix
Classifier: Programming Language :: Python :: 3.11
Classifier: Programming Language :: Python :: 3.12
Classifier: Programming Language :: Python :: 3.13
Classifier: Topic :: Scientific/Engineering :: Physics
Classifier: Topic :: Scientific/Engineering :: Chemistry
Requires-Python: <3.14,>=3.11
License-File: LICENSE.rst
License-File: AUTHORS.rst
Requires-Dist: numpy
Requires-Dist: pandas
Requires-Dist: openpyxl
Requires-Dist: click
Requires-Dist: moviepy
Dynamic: license-file
